fouriercoint/__init__.py
fouriercoint/core.py
fouriercoint/critical_values.py
fouriercoint/utils.py
fouriercoint-0.1.2.dist-info/licenses/LICENSE
fouriercoint-0.1.2.dist-info/METADATA
fouriercoint-0.1.2.dist-info/WHEEL
fouriercoint-0.1.2.dist-info/top_level.txt
fouriercoint-0.1.2.dist-info/RECORD
