Metadata-Version: 2.4
Name: fouriercoint
Version: 0.1.2
Summary: Fourier-based cointegration and unit-root testing utilities
Author-email: "Dr. Merwan Roudane" <merwanroudane920@gmail.com>
License-Expression: GPL-3.0-or-later
Project-URL: Homepage, https://github.com/merwanroudane/fouriercoint
Project-URL: Repository, https://github.com/merwanroudane/fouriercoint
Project-URL: Bug Reports, https://github.com/merwanroudane/fouriercoint/issues
Classifier: Intended Audience :: Science/Research
Classifier: Programming Language :: Python :: 3
Classifier: Programming Language :: Python :: 3.8
Classifier: Programming Language :: Python :: 3.9
Classifier: Programming Language :: Python :: 3.10
Classifier: Programming Language :: Python :: 3.11
Classifier: Programming Language :: Python :: 3.12
Classifier: Operating System :: OS Independent
Requires-Python: >=3.8
License-File: LICENSE
Requires-Dist: numpy>=1.21
Requires-Dist: scipy>=1.7
Dynamic: license-file
